{
  "os": "Linux-5.14.0-503.40.1.el9_5.x86_64-x86_64-with-glibc2.34",
  "python": "CPython 3.10.18",
  "startedAt": "2026-01-27T18:27:26.094535Z",
  "args": [
    "--max_chars=2000000000",
    "--vocab_size=65536",
    "--doc_cap=10000"
  ],
  "program": "-m scripts.tok_train",
  "git": {
    "remote": "https://github.com/unruli/chibu-chat.git",
    "commit": "eacd361380837b3e2367b2fd767b2d8e44ee0059"
  },
  "email": "c.okocha@ufl.edu",
  "root": "/orange/ufdatastudios/c.okocha/chibu-chat",
  "host": "c0906a-s25.ufhpc",
  "executable": "/orange/ufdatastudios/c.okocha/chibu-chat/.venv/bin/python",
  "cpu_count": 112,
  "cpu_count_logical": 112,
  "gpu": "NVIDIA B200",
  "gpu_count": 1,
  "disk": {
    "/": {
      "total": "41922297856",
      "used": "19787689984"
    }
  },
  "memory": {
    "total": "2163693277184"
  },
  "gpu_nvidia": [
    {
      "name": "NVIDIA B200",
      "memoryTotal": "192265846784",
      "cudaCores": 18944,
      "architecture": "Blackwell",
      "uuid": "GPU-1d68f287-cdce-cf2a-27df-c713ee913bfe"
    }
  ],
  "cudaVersion": "12.8",
  "slurm": {
    "cluster_name": "hipergator",
    "conf": "/opt/slurm/etc/slurm.conf",
    "cpu_bind": "quiet,mask_cpu:0x00000000000000000007F0000001",
    "cpu_bind_list": "0x00000000000000000007F0000001",
    "cpu_bind_type": "mask_cpu:",
    "cpu_bind_verbose": "quiet",
    "cpus_on_node": "8",
    "cpus_per_task": "8",
    "distribution": "block",
    "gpus": "1",
    "gpus_on_node": "1",
    "gtids": "0",
    "job_account": "ufdatastudios",
    "job_cpus_per_node": "8",
    "job_end_time": "1769556202",
    "job_gid": "4329",
    "job_gpus": "0",
    "job_id": "23901247",
    "job_name": "nanochat-tokenizer",
    "job_nodelist": "c0906a-s25",
    "job_num_nodes": "1",
    "job_partition": "hpg-b200",
    "job_qos": "ufdatastudios",
    "job_start_time": "1769538202",
    "job_uid": "2114",
    "job_user": "c.okocha",
    "jobid": "23901247",
    "launch_node_ipaddr": "172.16.139.189",
    "localid": "0",
    "mem_per_node": "65536",
    "nnodes": "1",
    "nodeid": "0",
    "nodelist": "c0906a-s25",
    "nprocs": "1",
    "ntasks": "1",
    "oom_kill_step": "0",
    "prio_process": "0",
    "procid": "0",
    "srun_comm_host": "172.16.139.189",
    "srun_comm_port": "46285",
    "step_gpus": "0",
    "step_id": "0",
    "step_launcher_port": "46285",
    "step_nodelist": "c0906a-s25",
    "step_num_nodes": "1",
    "step_num_tasks": "1",
    "step_tasks_per_node": "1",
    "stepid": "0",
    "submit_dir": "/orange/ufdatastudios/c.okocha/chibu-chat",
    "submit_host": "login9.ufhpc",
    "task_pid": "1647861",
    "tasks_per_node": "1",
    "tmpdir": "/scratch/local/23901247",
    "topology_addr": "ibswb200.ibsw0908.c0906a-s25",
    "topology_addr_pattern": "switch.switch.node",
    "tres_per_task": "cpu=8",
    "umask": "0022"
  },
  "writerId": "92e3q9rbob13lzam95qiutce8fps0jb1"
}